librestapi/__init__.py
librestapi/client.py
librestapi/resource.py
tests/__init__.py
tests/test_client.py
tests/test_resource.py
librestapi-0.0.2.dist-info/METADATA
librestapi-0.0.2.dist-info/WHEEL
librestapi-0.0.2.dist-info/top_level.txt
librestapi-0.0.2.dist-info/RECORD
